HowToMakeAnOperatingSystem/README.md
HowToMakeAnOperatingSystem/__init__.py
HowToMakeAnOperatingSystem/__main__.py
HowToMakeAnOperatingSystem/file.epub
HowToMakeAnOperatingSystem/index.html
HowToMakeAnOperatingSystem/css/__init__.py
HowToMakeAnOperatingSystem/css/annotations.css
HowToMakeAnOperatingSystem/css/main.css
HowToMakeAnOperatingSystem/css/normalize.css
HowToMakeAnOperatingSystem/css/popup.css
HowToMakeAnOperatingSystem/font/__init__.py
HowToMakeAnOperatingSystem/font/fontello.eot
HowToMakeAnOperatingSystem/font/fontello.svg
HowToMakeAnOperatingSystem/font/fontello.ttf
HowToMakeAnOperatingSystem/font/fontello.woff
HowToMakeAnOperatingSystem/img/__init__.py
HowToMakeAnOperatingSystem/img/annotator-glyph-sprite.png
HowToMakeAnOperatingSystem/img/annotator-icon-sprite.png
HowToMakeAnOperatingSystem/img/apple-touch-icon.png
HowToMakeAnOperatingSystem/img/cancelfullscreen.png
HowToMakeAnOperatingSystem/img/close.png
HowToMakeAnOperatingSystem/img/fullscreen.png
HowToMakeAnOperatingSystem/img/loader.gif
HowToMakeAnOperatingSystem/img/menu-icon.png
HowToMakeAnOperatingSystem/img/save.png
HowToMakeAnOperatingSystem/img/saved.png
HowToMakeAnOperatingSystem/img/settings-s.png
HowToMakeAnOperatingSystem/img/settings.png
HowToMakeAnOperatingSystem/img/star.png
HowToMakeAnOperatingSystem/js/__init__.py
HowToMakeAnOperatingSystem/js/epub.js
HowToMakeAnOperatingSystem/js/epub.min.js
HowToMakeAnOperatingSystem/js/epub.min.map
HowToMakeAnOperatingSystem/js/hooks.min.js
HowToMakeAnOperatingSystem/js/hooks.min.map
HowToMakeAnOperatingSystem/js/reader.js
HowToMakeAnOperatingSystem/js/reader.js.map
HowToMakeAnOperatingSystem/js/reader.min.js
HowToMakeAnOperatingSystem/js/reader.min.map
HowToMakeAnOperatingSystem/js/hooks/__init__.py
HowToMakeAnOperatingSystem/js/hooks/extensions/__init__.py
HowToMakeAnOperatingSystem/js/hooks/extensions/highlight.js
HowToMakeAnOperatingSystem/js/libs/__init__.py
HowToMakeAnOperatingSystem/js/libs/jquery.min.js
how_to_make_an_operating_system-2024.3.2.0.dist-info/METADATA
how_to_make_an_operating_system-2024.3.2.0.dist-info/WHEEL
how_to_make_an_operating_system-2024.3.2.0.dist-info/entry_points.txt
how_to_make_an_operating_system-2024.3.2.0.dist-info/top_level.txt
how_to_make_an_operating_system-2024.3.2.0.dist-info/RECORD
